pypi_stats_timeline
