Metadata-Version: 2.1
Name: pypi-stats-timeline
Version: 1.1.0
Summary: Fetch, maintain and query a timeline of downloads from Python's PyPI Package indexes used by pip
Home-page: https://github.com/talwrii/pypi-stats-timeline
Author: @readwithai
Author-email: talwrii@gmail.com
License: MIT
Keywords: python,cli,PyPI,timeline
